pynostr/__init__.py
pynostr/_version.py
pynostr/base_relay.py
pynostr/bech32.py
pynostr/cli.py
pynostr/contact_list.py
pynostr/delegation.py
pynostr/encrypted_dm.py
pynostr/event.py
pynostr/exception.py
pynostr/filters.py
pynostr/key.py
pynostr/message_pool.py
pynostr/message_type.py
pynostr/metadata.py
pynostr/pow.py
pynostr/relay.py
pynostr/relay_list.py
pynostr/relay_manager.py
pynostr/report.py
pynostr/subscription.py
pynostr/utils.py
pynostr/websocket_relay.py
pynostr/websocket_relay_manager.py
pynostr-0.6.2.dist-info/LICENSE
pynostr-0.6.2.dist-info/METADATA
pynostr-0.6.2.dist-info/WHEEL
pynostr-0.6.2.dist-info/entry_points.txt
pynostr-0.6.2.dist-info/top_level.txt
pynostr-0.6.2.dist-info/RECORD
