Metadata-Version: 2.1
Name: pynostr
Version: 0.6.2
Summary: Python Library for nostr.
Author-email: Holger Nahrstaedt <nahrstaedt@gmail.com>
License: MIT License
Project-URL: Homepage, https://github.com/holgern/pynostr
Keywords: nostr
Classifier: Intended Audience :: Developers
Classifier: License :: OSI Approved :: MIT License
Classifier: Operating System :: OS Independent
Classifier: Programming Language :: Python :: 3
Classifier: Programming Language :: Python :: 3.7
Classifier: Programming Language :: Python :: 3.8
Classifier: Programming Language :: Python :: 3.9
Classifier: Programming Language :: Python :: 3.10
Classifier: Programming Language :: Python :: 3.11
Classifier: Topic :: Software Development :: Libraries
Requires-Python: >3.7.0
License-File: LICENSE
Requires-Dist: coincurve (>=1.8.0)
Requires-Dist: cryptography (>=37.0.4)
Requires-Dist: tlv8
Requires-Dist: typer
Requires-Dist: tornado
Requires-Dist: rich
Requires-Dist: requests
Provides-Extra: websocket-client
Requires-Dist: websocket-client (>=1.3.3) ; extra == 'websocket-client'
